bouchon/__init__.py
bouchon/__main__.py
bouchon-0.1.4.dist-info/WHEEL
bouchon-0.1.4.dist-info/METADATA
bouchon-0.1.4.dist-info/RECORD
